ec2_ssh/__init__.py
ec2_ssh/cli/__init__.py
ec2_ssh/ec2_helpers/__init__.py
ssh_ec2-0.0.2.data/scripts/ssh_ec2
ssh_ec2-0.0.2.dist-info/LICENSE
ssh_ec2-0.0.2.dist-info/METADATA
ssh_ec2-0.0.2.dist-info/WHEEL
ssh_ec2-0.0.2.dist-info/top_level.txt
ssh_ec2-0.0.2.dist-info/RECORD
