Metadata-Version: 2.1
Name: ssh-ec2
Version: 0.0.2
Summary: A simple AWS ec2 host discovery and ssh script
Home-page: https://github.com/grahamhar/ssh-ec2/
Author: grahamhar
License: UNKNOWN
Project-URL: Bug Reports, https://github.com/grahamhar/ssh-ec2/issues
Project-URL: Source, https://github.com/grahamhar/ssh-ec2/
Keywords: aws ec2 ssh
Platform: UNKNOWN
Classifier: Development Status :: 3 - Alpha
Classifier: Intended Audience :: Developers
Classifier: Topic :: Software Development :: Build Tools
Classifier: License :: OSI Approved :: Apache Software License
Classifier: Programming Language :: Python :: 3
Requires-Dist: awscli
Requires-Dist: boto3
Requires-Dist: click
Requires-Dist: click-completion
Provides-Extra: dev
Requires-Dist: pytest; extra == 'dev'
Requires-Dist: pytest-cov; extra == 'dev'
Requires-Dist: coveralls; extra == 'dev'
